huawei_modem_api_client-1.1.5.data/data/requirements.txt
huaweisms/__init__.py
huaweisms/api/__init__.py
huaweisms/api/common.py
huaweisms/api/config.py
huaweisms/api/device.py
huaweisms/api/dialup.py
huaweisms/api/monitoring.py
huaweisms/api/sms.py
huaweisms/api/user.py
huaweisms/api/ussd.py
huaweisms/api/webserver.py
huaweisms/api/wlan.py
huaweisms/xml/__init__.py
huaweisms/xml/util.py
huawei_modem_api_client-1.1.5.dist-info/LICENSE.md
huawei_modem_api_client-1.1.5.dist-info/METADATA
huawei_modem_api_client-1.1.5.dist-info/WHEEL
huawei_modem_api_client-1.1.5.dist-info/top_level.txt
huawei_modem_api_client-1.1.5.dist-info/RECORD
