Metadata-Version: 2.1
Name: huawei-modem-api-client
Version: 1.1.5
Summary: huaweisms is a python api client for Huawei Modems.
Home-page: https://github.com/pablo/huawei-modem-python-api-client
Author: Pablo Santa Cruz, Mkhanyisi Madlavana
Author-email: pablo@roshka.com.py, mkhanyisi@gmail.com
License: UNKNOWN
Download-URL: https://github.com/dopstar/huawei-modem-python-api-client/tarball/1.1.5
Keywords: Huawei,Modem,HTTP API Client,API Client,Router
Platform: UNKNOWN
Classifier: Development Status :: 5 - Production/Stable
Classifier: Intended Audience :: Developers
Classifier: Natural Language :: English
Classifier: Programming Language :: Python :: 2.7
Classifier: Programming Language :: Python :: 3.6
Classifier: Programming Language :: Python :: 3.7
Classifier: Programming Language :: Python :: 3.8
Classifier: Programming Language :: Python :: 3.9
Classifier: Programming Language :: Python :: 3.10
Classifier: License :: OSI Approved :: MIT License
Classifier: Operating System :: MacOS
Classifier: Operating System :: POSIX :: Linux
Classifier: Operating System :: Microsoft :: Windows
Classifier: Topic :: Software Development :: Version Control :: Git
Classifier: Programming Language :: Python :: Implementation :: CPython
Provides-Extra: testing
Provides-Extra: linting
License-File: LICENSE.md
